tektronixsg/__init__.py
tektronixsg/channel.py
tektronixsg/generator.py
tektronixsg-0.1.0.dist-info/AUTHORS.rst
tektronixsg-0.1.0.dist-info/LICENSE
tektronixsg-0.1.0.dist-info/METADATA
tektronixsg-0.1.0.dist-info/WHEEL
tektronixsg-0.1.0.dist-info/top_level.txt
tektronixsg-0.1.0.dist-info/RECORD
