Metadata-Version: 2.1
Name: tektronixsg
Version: 0.1.0
Summary: Interface for Tektronix signal generators.
Home-page: https://github.com/emtpb/tektronixsg/
Author: Kevin Koch
Author-email: kevink2@mail.uni-paderborn.de
License: BSD
Classifier: Development Status :: 2 - Pre-Alpha
Classifier: Intended Audience :: Science/Research
Classifier: License :: OSI Approved :: BSD License
Classifier: Programming Language :: Python :: 3
Classifier: Topic :: Scientific/Engineering
Requires-Python: >=3
License-File: LICENSE
License-File: AUTHORS.rst
Requires-Dist: pyvisa
Requires-Dist: pyvisa-py ; sys_platform == "linux"
Requires-Dist: pyusb ; sys_platform == "linux"
